graphene_django_sentry/__init__.py
graphene_django_sentry/views.py
graphene_django_sentry-0.2.0.dist-info/DESCRIPTION.rst
graphene_django_sentry-0.2.0.dist-info/METADATA
graphene_django_sentry-0.2.0.dist-info/RECORD
graphene_django_sentry-0.2.0.dist-info/WHEEL
graphene_django_sentry-0.2.0.dist-info/metadata.json
graphene_django_sentry-0.2.0.dist-info/top_level.txt
