Metadata-Version: 2.0
Name: graphene-django-sentry
Version: 0.2.0
Summary: Capture Sentry exceptions in Graphene views
Home-page: https://github.com/phalt/graphene-django-sentry
Author: Paul Hallett
Author-email: paulandrewhallett@gmail.com
License: MIT license
Keywords: GraphQL graphene django sentry
Platform: UNKNOWN
Classifier: Development Status :: 4 - Beta
Classifier: Intended Audience :: Developers
Classifier: License :: OSI Approved :: MIT License
Classifier: Natural Language :: English
Classifier: Programming Language :: Python :: 3.6
Classifier: Programming Language :: Python :: 3.7
Requires-Dist: graphene-django (==2.2.0)
Requires-Dist: sentry-sdk (==0.5.2)
